{
  "spec": {
    "language": "lv",
    "version": 1,
    "section": "auth"
  },
  "translations": {
    "base_layout": {
      "logo_alt": "${business_name} logotips",
      "credit_powered_by": "Nodrošina",
      "credit_logo_link": "Apmeklēt Kinde",
      "skip_link_main": "Pāriet uz galveno saturu"
    },
    "mfa_sms_page": {
      "page_title": "Ievadiet tālruņa numuru | ${business_name}",
      "heading": "Autentifikācija caur SMS",
      "description": "Pievienojiet tālruņa numuru, lai saņemtu kodus ar sms",
      "continue_button": "Turpināt",
      "phone_input_label": "Tālruņa numurs",
      "phone_input_help_text": "Atstājiet ārā sākuma 0",
      "phone_input_error_required": "Ievadiet tālruņa numuru",
      "phone_input_error_invalid_region": "Numurs nav derīgs šim reģionam",
      "phone_input_error_invalid_format": "Ievadiet tikai ciparus bez atstarpēm, izņemot sākuma 0",
      "country_input_label": "Valsts vai reģions",
      "country_input_error_invalid": "Nepieciešama derīga valsts",
      "choose_another_method_link": "Izvēlēties citu metodi"
    },
    "mfa_email_page": {
      "page_title": "Ievadiet e-pastu | ${business_name}",
      "heading": "Autentifikācija caur E-pastu",
      "description": "Pievienojiet e-pasta adresi, lai saņemtu kodus ar e-pastu",
      "continue_button": "Turpināt",
      "email_input_label": "E-pasts",
      "email_input_error_required": "E-pasts nevar tikt atstāts tukšs",
      "email_input_error_invalid": "Ievadiet derīgu e-pasta adresi",
      "email_input_error_email_in_use": "E-pasta adrese tiek izmantota"
    },
    "index": {
      "page_title": "Sākumlapa | ${business_name}",
      "heading": "Laipni lūdzam ${business_name}",
      "description": "Šeit pagaidām nav ko redzēt. Bet drīz būs pieejama lieliska sākumlapa.",
      "sign_in_button": "Pierakstīties",
      "manage_business_button": "Pārvaldīt ${business_name} kontu"
    },
    "sign_in_page": {
      "page_title": "Pierakstīties | ${business_name}",
      "heading": "Laipni atgriezies",
      "description": "Ievadiet savu e-pastu un mēs nosūtīsim pierakstīšanās kodu.",
      "email_input_label": "E-pasts",
      "email_input_error_invalid": "Ievadiet derīgu e-pastu",
      "email_input_error_required": "E-pasts ir nepieciešams",
      "email_input_error_invitation_mismatch": "E-pastam jāsakrīt ar to, uz kuru tika nosūtīta uzaicinājuma",
      "email_input_error_no_account_found": "Ar šo e-pastu nav atrasts neviens konts",
      "auth_form_error_no_auth_methods_enabled": "Diemžēl, šobrīd nevaram jūs autentificēt.",
      "continue_with_email_button": "Turpināt",
      "auth_block_separator": "Vai",
      "continue_with_social_provider_button": "Turpināt ar ${social_provider_name}",
      "continue_with_enterprise_provider_button": "Turpināt ar ${enterprise_provider_name}",
      "no_account_description": "Nav konta?",
      "no_account_link": "Izveidot vienu"
    },
    "sign_up_page": {
      "page_title": "Reģistrēties | ${business_name}",
      "heading": "Izveidot kontu",
      "description": "Prieks jūs šeit redzēt",
      "invitation_description": "Jūs esat uzaicināts pievienoties ${business_name}. Lūdzu, pierakstieties vai reģistrējieties, lai pieņemtu uzaicinājumu.",
      "first_name_input_label": "Vārds",
      "first_name_input_error_required": "Lūdzu, ievadiet savu vārdu",
      "last_name_input_label": "Uzvārds",
      "last_name_input_error_required": "Lūdzu, ievadiet savu uzvārdu",
      "email_input_label": "E-pasts",
      "email_input_error_required": "E-pasts ir nepieciešams",
      "email_input_error_invalid": "Ievadiet derīgu e-pastu",
      "email_input_error_invitation_mismatch": "E-pastam jāsakrīt ar to, uz kuru tika nosūtīta uzaicinājuma",
      "continue_with_email_button": "Izveidot jūsu kontu",
      "auth_block_separator": "Vai",
      "continue_with_social_provider_button": "Turpināt ar ${social_provider_name}",
      "continue_with_enterprise_provider_button": "Turpināt ar ${enterprise_provider_name}",
      "already_have_an_account_description": "Jau ir konts?",
      "already_have_an_account_link": "Pierakstīties",
      "disclaimer": "Turpinot, jūs piekrītat mūsu politikai",
      "disclaimer_privacy_link": "Privātuma politika",
      "disclaimer_terms_of_use_link": "Lietošanas noteikumi",
      "disclaimer_clickwrap_input_label": "Pieņemt politiku",
      "disclaimer_clickwrap_error_required": "Lai turpinātu, jums ir jālasa un jāpieņem politika",
      "disclaimer_dialog_heading": "Pieņemt, lai turpinātu",
      "disclaimer_dialog_description": "Lai turpinātu reģistrāciju, mums ir nepieciešams, lai jūs izlasītu un pieņemtu mūsu politiku",
      "auth_form_error_terms_not_accepted": "Jums ir jālasa un jāpieņem politika, lai turpinātu",
      "auth_form_error_no_auth_methods_enabled": "Diemžēl, šobrīd nevaram jūs autentificēt.",
      "auth_form_error_org_not_accepting_registrations": "Norādītā organizācija nepieņem reģistrācijas"
    },
    "choose_mfa_method_page": {
      "page_title": "Izvēlēties MFA opciju | ${business_name}",
      "heading": "Pārbaudīt jūsu identitāti",
      "description": "Izvēlieties autentifikācijas metodi",
      "authenticator_app_button": "Autentifikatora lietotne",
      "sms_button": "SMS",
      "email_button": "E-pasts",
      "do_not_use_mfa_link": "Neizmantot daudzfaktoru autentifikāciju"
    },
    "account_locked_page": {
      "page_title": "Konts bloķēts | ${business_name}",
      "heading": "Konts ir bloķēts",
      "description": "Jūs esat ievadījis nepareizu kodu pārāk daudzas reizes, un jūsu konts ir bloķēts uz ${lockout_duration_minutes} minūtēm",
      "back_to_home_button": "Atgriezties atpakaļ",
      "back_to_sign_in_button": "Pierakstīties"
    },
    "password_setup_page": {
      "page_title": "Iestatīt paroli | ${business_name}",
      "heading": "Paroles iestatīšana",
      "description": "Lūdzu, iestatiet savu paroli.",
      "password_input_label": "Parole",
      "password_input_error_too_common": "Šī parole ir ļoti izplatīta. Padariet to grūtāk uzminamu.",
      "password_input_error_too_short": "Parolēm jābūt vismaz 8 rakstzīmes garām",
      "password_input_error_extra_space": "Parole nevar sākties vai beigties ar atstarpi",
      "confirm_password_input_label": "Apstiprināt paroli",
      "confirm_password_input_error_mismatch": "Pārliecinieties, ka paroles ir identiskas",
      "continue_button": "Turpināt",
      "password_input_error_unknown_error": "Autentifikācijas kļūda"
    },
    "password_reset_page": {
      "page_title": "Iestatīt paroli | ${business_name}",
      "heading": "Paroles iestatīšana",
      "description": "Lūdzu, iestatiet savu paroli.",
      "password_input_label": "Parole",
      "password_input_error_too_common": "Šī parole ir ļoti izplatīta. Padariet to grūtāk uzminamu.",
      "password_input_error_too_short": "Parolēm jābūt vismaz 8 rakstzīmes garām",
      "password_input_error_extra_space": "Parole nevar sākties vai beigties ar atstarpi",
      "confirm_password_input_label": "Apstiprināt paroli",
      "confirm_password_input_error_mismatch": "Pārliecinieties, ka paroles ir identiskas",
      "continue_button": "Turpināt",
      "password_input_error_unknown_error": "Autentifikācijas kļūda"
    },
    "recovery_codes_page": {
      "page_title": "Atjaunošanas kodi | ${business_name}",
      "heading": "Gandrīz pabeigts",
      "description": "Nokopējiet šos atjaunošanas kodus un glabājiet tos drošā vietā. Jums tie būs nepieciešami, ja jebkad vajadzēs pierakstīties bez savas ierīces.",
      "copy_button": "Kopēt visus",
      "print_button": "Izprintēt",
      "continue_button": "Turpināt",
      "download_button": "Lejupielādēt .txt",
      "recovery_codes_page_error_no_codes": "Nav kodu, ko parādīt",
      "recovery_codes_page_error_already_viewed": "Izskatās, ka jūs jau esat reizi apskatījis atjaunošanas kodus, tāpēc mēs nevaram tos vēlreiz parādīt. Ja nepieciešama palīdzība pierakstīšanās laikā, sazinieties ar savu konta administratoru.",
      "back_home_button": "Atpakaļ uz sākumlapu"
    },
    "subscribe_form_widget": {
      "page_title": "Abonēšana",
      "heading": "Esi informēts",
      "description": "Uzziniet par produktu atjauninājumiem, ziņām un notikumiem",
      "name_input_label": "Vārds",
      "name_input_error_required": "Lūdzu, ievadiet vārdu",
      "name_input_error_exceeds_max_length": "Vārds ir pārāk garš",
      "email_input_label": "E-pasts",
      "email_input_error_invalid": "Ievadiet derīgu e-pastu",
      "email_input_error_required": "E-pasts ir nepieciešams",
      "email_input_error_duplicate_email_found": "Šis e-pasts jau ir abonēts",
      "continue_button": "Pierakstīties",
      "success_heading": "Veiksmīgi! Laipni lūdzam ciklā.",
      "credit_powered_by": "Nodrošina"
    },
    "password_verify_page": {
      "page_title": "Pārbaudīt paroli | ${business_name}",
      "heading": "Ievadiet savu paroli",
      "description": "Ievadiet savu paroli priekš ${email_address}",
      "password_input_label": "Parole",
      "password_input_error_required": "Lūdzu, ievadiet savu paroli",
      "password_input_error_incorrect": "Lūdzu, norādiet derīgu paroli",
      "password_input_error_too_short": "Parolēm jābūt vismaz 8 rakstzīmes garām",
      "password_input_error_unknown_error": "Autentifikācijas kļūda",
      "continue_button": "Turpināt",
      "cant_sign_in_description": "Nevarat pierakstīties?",
      "cant_sign_in_link": "Atiestatīt paroli"
    },
    "sms_verify_code_page": {
      "page_title": "Daudzfaktoru autentifikācija | ${business_name}",
      "heading": "Pārbaudīt tālruņa numuru",
      "description": "Ievadiet kodu, ko tikko nosūtījām uz ${phone_number}",
      "code_input_label": "Kods",
      "code_input_error_expired_code": "Jūsu apstiprināšanas kods ir beidzis derīgumu, lūdzu, pieprasiet jaunu",
      "code_input_error_incorrect_code": "Lūdzu, ievadiet derīgu apstiprināšanas kodu",
      "code_input_error_incorrect_code_length": "Apstiprināšanas kodam jābūt 6 cipariem",
      "code_input_error_resend_requested_too_soon": "Nevar nosūtīt citu kodu tik ātri. Lūdzu, mēģiniet vēlreiz vēlāk",
      "confirmation_code_input_error_unknown_error": "Autentifikācijas kļūda",
      "continue_button": "Apstiprināt",
      "didnt_receive_a_code_description": "Nesaņēmāt kodu?",
      "didnt_receive_a_code_link": "Atkārtoti nosūtīt kodu",
      "choose_another_method_link": "Izvēlēties citu metodi"
    },
    "recovery_code_verify_page": {
      "page_title": "Izmantot atjaunošanas kodu | ${business_name}",
      "heading": "Atjaunošanas kods",
      "description": "Ievadiet vienu no atjaunošanas kodiem, ko saņēmāt pirmreizējās reģistrācijas laikā.",
      "recovery_code_input_label": "Atjaunošanas kods",
      "continue_button": "Turpināt",
      "choose_another_method_link": "Izvēlēties citu metodi",
      "recovery_code_input_error_unknown_error": "Problēma ar šī atjaunošanas koda autentifikāciju",
      "recovery_code_input_error_required": "Ievadiet savu atjaunošanas kodu",
      "recovery_code_input_error_too_short": "Ievadiet vismaz 9 rakstzīmju garu atjaunošanas kodu",
      "recovery_code_input_error_invalid": "Ievadiet derīgu atjaunošanas kodu"
    },
    "verification_code_sms": {
      "description": "${generated_code} ir vienreizējais kods, lai pierakstītos ${business_name}\n\n@${receiver_domain} #${generated_code}"
    },
    "choose_organization_page": {
      "page_title": "Izvēlēties organizāciju | ${business_name}",
      "heading": "Kur jūs vēlaties pierakstīties?",
      "choose_org_select_label": "Pierakstīt mani",
      "choose_org_select_error_invalid": "Nederīga organizācija",
      "continue_button": "Turpināt"
    },
    "request_access_page": {
      "page_title": "Saņemt paziņojumu vispirms",
      "heading": "Mēs jūs informēsim un nosūtīsim ielūgumu, kad piekļuve būs pieejama",
      "description": "Mēs jūs informēsim un paziņosim, kad jūsu ielūgums būs gatavs",
      "continue_button": "Pieprasīt piekļuvi",
      "success_heading": "Paldies, ka pieprasījāt piekļuvi. Mēs esam jūs pievienojuši mūsu sarakstam un drīz sūtīsim atjauninājumus.",
      "first_name_input_label": "Vārds",
      "first_name_input_error_required": "Lūdzu, ievadiet savu vārdu",
      "last_name_input_label": "Uzvārds",
      "email_input_label": "E-pasts",
      "email_input_error_invalid": "Ievadiet derīgu e-pastu",
      "email_input_error_required": "E-pasts ir nepieciešams",
      "email_input_error_duplicate_email_found": "Šis e-pasts jau ir reģistrēts",
      "success_description": "Paldies, ka pieprasījāt piekļuvi ${business_name}. Mēs esam jūs pievienojuši mūsu abonentu sarakstam un informēsim jūs, tiklīdz ielūgums būs pieejams.",
      "success_link_url": "Atpakaļ uz ${business_name} mājaslapu"
    },
    "sign_in_confirm_code_page": {
      "page_title": "Apstiprināt kodu | ${business_name}",
      "heading": "Pārbaudiet savu e-pastu",
      "description": "Ievadiet kodu, ko tikko nosūtījām uz ${email_address}",
      "resent_code": "Mēs tikko nosūtījām jaunu kodu uz ${email_address}",
      "code_input_label": "Kods",
      "code_input_error_expired_code": "Jūsu apstiprināšanas kods ir beidzis derīgumu, lūdzu, pieprasiet jaunu",
      "code_input_error_incorrect_code": "Lūdzu, ievadiet derīgu apstiprināšanas kodu",
      "code_input_error_incorrect_code_length": "Apstiprināšanas kodam jābūt 6 cipariem",
      "code_input_error_resend_requested_too_soon": "Nevar nosūtīt citu kodu tik ātri. Lūdzu, mēģiniet vēlreiz vēlāk",
      "continue_button": "Turpināt",
      "didnt_receive_a_code_link": "Atkārtoti nosūtīt kodu",
      "didnt_receive_a_code_description": "Nesaņēmāt kodu?",
      "warning_too_many_incorrect_attempts": "Tika ievadīti pārāk daudzi nepareizi kodi, tāpēc mēs nosūtījām jaunu kodu uz ${email_address}",
      "choose_another_method_link": "Izvēlēties citu metodi"
    },
    "sign_up_confirm_code_page": {
      "page_title": "Apstiprināt kodu | ${business_name}",
      "heading": "Pārbaudiet savu e-pastu",
      "description": "Ievadiet kodu, ko tikko nosūtījām uz ${email_address}",
      "finish_sign_up_code_description": "Lai turpinātu, ievadiet kodu, ko tikko nosūtījām uz ${email_address}",
      "continue_sign_up_code_description": "Lai turpinātu, ievadiet kodu, ko tikko nosūtījām uz ${email_address}",
      "resent_code": "Mēs tikko nosūtījām jaunu kodu uz ${email_address}",
      "code_input_label": "Kods",
      "code_input_error_expired_code": "Jūsu apstiprināšanas kods ir beidzis derīgumu, lūdzu, pieprasiet jaunu",
      "code_input_error_incorrect_code": "Lūdzu, ievadiet derīgu apstiprināšanas kodu",
      "code_input_error_incorrect_code_length": "Apstiprināšanas kodam jābūt 6 cipariem",
      "code_input_error_resend_requested_too_soon": "Nevar nosūtīt citu kodu tik ātri. Lūdzu, mēģiniet vēlreiz vēlāk",
      "didnt_receive_a_code_description": "Nesaņēmāt kodu?",
      "didnt_receive_a_code_link": "Atkārtoti nosūtīt kodu",
      "continue_button": "Turpināt",
      "warning_too_many_incorrect_attempts": "Tika ievadīti pārāk daudzi nepareizi kodi, tāpēc mēs tikko nosūtījām jaunu kodu uz ${email_address}",
      "choose_another_method_link": "Izvēlēties citu metodi"
    },
    "authenticator_app_manual_page": {
      "page_title": "Autentifikatora lietotne | ${business_name}",
      "heading": "Autentifikatora lietotne",
      "description": "Ievadiet sekojošo kodu savā izvēlētajā autentifikatora lietotnē. Tad ievadiet vienreizlietošanas kodu, ko saņemat zemāk.",
      "code_input_label": "Vienreizlietošanas kods",
      "code_input_error_required": "Lūdzu, ievadiet derīgu verifikācijas kodu",
      "code_input_error_expired_code": "Jūsu apstiprināšanas kods ir beidzis derīgumu, lūdzu, pieprasiet jaunu",
      "code_input_error_incorrect_code_length": "Apstiprināšanas kodam jābūt 6 cipariem",
      "code_input_error_incorrect_code": "Lūdzu, ievadiet derīgu apstiprināšanas kodu",
      "continue_button": "Turpināt",
      "choose_another_method_link": "Izvēlēties citu metodi"
    },
    "authenticator_app_qr_code_page": {
      "page_title": "Daudzfaktoru autentifikācija | ${business_name}",
      "heading": "Autentifikatora lietotne",
      "description": "Noskenējiet zemāk redzamo QR kodu, izmantojot jūsu izvēlēto autentifikatora lietotni. Ievadiet vienreizlietošanas kodu, ko saņemat zemāk.",
      "code_input_label": "Vienreizlietošanas kods",
      "code_input_error_required": "Lūdzu, ievadiet derīgu verifikācijas kodu",
      "code_input_error_expired_code": "Jūsu apstiprināšanas kods ir beidzis derīgumu, lūdzu, pieprasiet jaunu",
      "code_input_error_incorrect_code": "Lūdzu, ievadiet derīgu apstiprināšanas kodu",
      "code_input_error_incorrect_code_length": "Apstiprināšanas kodam jābūt 6 cipariem",
      "continue_button": "Turpināt",
      "trouble_scanning_link": "Problēmas ar skenēšanu?",
      "choose_another_method_link": "Izvēlēties citu metodi"
    },
    "authenticator_app_verify_code_page": {
      "page_title": "Daudzfaktoru autentifikācija | ${business_name}",
      "heading": "Autentifikatora lietotne",
      "description": "Atveriet jūsu apstiprināto autentifikatora lietotni un ievadiet kodu zemāk",
      "code_input_label": "Vienreizlietošanas kods",
      "code_input_error_required": "Lūdzu, ievadiet derīgu verifikācijas kodu",
      "code_input_error_expired_code": "Jūsu apstiprināšanas kods ir beidzis derīgumu, lūdzu, pieprasiet jaunu",
      "code_input_error_incorrect_code": "Lūdzu, ievadiet derīgu apstiprināšanas kodu",
      "code_input_error_incorrect_code_length": "Apstiprināšanas kodam jābūt 6 cipariem",
      "continue_button": "Turpināt",
      "choose_another_method_link": "Izvēlēties citu metodi"
    },
    "email_address_verification_email": {
      "email_body": "Šis kods beigsies 2 stundu laikā. Ja uzskatāt, ka nevajadzētu saņemt šo e-pastu, to varat droši ignorēt.",
      "email_preview": "Lūdzu, izmantojiet zemāk esošo kodu, lai apstiprinātu savu e-pasta adresi un turpinātu ${business_name}",
      "email_subject": "E-pasta verifikācijas kods",
      "email_greeting": "Sveiki,",
      "email_disclaimer": "Jūs saņēmāt šo e-pastu, jo pieprasījāt apstiprināšanas kodu no ${business_name}"
    },
    "general_errors": {
      "page_title": "Autentifikācijas kļūda",
      "heading": "Autentifikācijas kļūda",
      "account_not_found": "Konts nav atrasts.",
      "action_allowed_only_once": "Pieprasītā darbība var tikt veikta tikai vienreiz.",
      "no_organization_access": "Atvainojiet, jums nav piekļuves šai organizācijai.",
      "operation_not_permitted": "Pieprasītā darbība nevar tikt pabeigta.",
      "back_to_home_button": "Atgriezties atpakaļ",
      "back_to_sign_in_button": "Pierakstīties"
    },
    "account_not_found_page": {
      "page_title": "Konts nav atrasts",
      "heading": "Mēs nevaram atrast jūsu kontu",
      "description": "Mums vajag vēl dažus detalizētus datus, lai pabeigtu jūsu konta izveidi.",
      "description_sign_ups_disabled": "Mēģiniet izmantot citu kontu vai pierakstīšanās opciju",
      "description_social": "Vai vēlaties izveidot jaunu kontu ar savu ${social_provider_name} kontu?",
      "description_credential": "Vai vēlaties tagad izveidot jaunu kontu ar ${credential}?",
      "continue_button": "Izveidot kontu",
      "back_button": "Atpakaļ uz pierakstīšanos",
      "sign_in_another_way_separator": "vai",
      "sign_in_another_way_link": "pierakstīties citādi"
    },
    "phone_number_component": {
      "phone_input_label": "Tālruņa numurs",
      "country_select_label": "Valsts",
      "use_email_link": "Pārslēgties uz e-pastu",
      "use_phone_link": "Pārslēgties uz tālruņa numuru",
      "phone_input_error_sms_limit_reached": "Nevar nosūtīt kodu. SMS ziņojumu pakalpojums nav iestatīts. Pierakstieties, izmantojot citu metodi.",
      "phone_input_error_invalid_country_code": "Nederīgs valsts kods. Izvēlieties no valstu saraksta.",
      "phone_input_error_required": "Tālruņa numurs nevar būt tukšs",
      "phone_input_error_invalid_format": "Ievadiet derīgu numuru bez atstarpēm vai valsts prefiksa",
      "phone_input_error_no_account_found": "Ar šo tālruņa numuru nav atrasts neviens konts"
    }
  }
}
