{
  "spec": {
    "language": "ms",
    "version": 1,
    "section": "auth"
  },
  "translations": {
    "base_layout": {
      "logo_alt": "${business_name} logo",
      "credit_powered_by": "Dikuasakan oleh",
      "credit_logo_link": "Lawati Kinde",
      "skip_link_main": "Langkau ke kandungan utama"
    },
    "mfa_sms_page": {
      "page_title": "Masukkan nombor telefon | ${business_name}",
      "heading": "Sahkan melalui SMS",
      "description": "Tambah nombor telefon untuk menerima kod melalui SMS",
      "continue_button": "Teruskan",
      "phone_input_label": "Nombor telefon",
      "phone_input_help_text": "Tanpa nombor 0 di hadapan",
      "phone_input_error_required": "Masukkan nombor telefon",
      "phone_input_error_invalid_region": "Nombor tidak sah untuk kawasan ini",
      "phone_input_error_invalid_format": "Hanya masukkan digit tanpa jarak, termasuklah nombor 0 di hadapan",
      "country_input_label": "Negara atau kawasan",
      "country_input_error_invalid": "Negara yang sah adalah diperlukan",
      "choose_another_method_link": "Sila pilih kaedah yang lain"
    },
    "auth_error_page": {
      "page_title": "Ralat Pengesahan",
      "heading": "Ralat Pengesahan"
    },
    "secret_page": {
      "page_title": "Laman Utama | ${business_name}",
      "heading": "Selamat datang ke ${business_name}",
      "description": "Tiada apa-apa untuk dilihat di sini buat masa ini. Tetapi sesuatu yang hebat akan datang tidak lama lagi",
      "sign_in_button": "Daftar masuk",
      "manage_business_button": "Uruskan ${business_name} akaun"
    },
    "sign_in_page": {
      "page_title": "Daftar masuk | ${business_name}",
      "heading": "Selamat kembali",
      "description": "Masukkan e-mel anda dan kami akan menghantar kod daftar masuk.",
      "email_input_label": "E-mel",
      "email_input_error_invalid": "Masukkan e-mel yg sah",
      "email_input_error_required": "E-mel diperlukan",
      "email_input_error_invitation_mismatch": "E-mel mesti sepadan dengan e-mel yang dihantar jemputan kepada anda",
      "email_input_error_no_account_found": "Tiada akaun dijumpai dengan e-mel ini",
      "auth_form_error_no_auth_methods_enabled": "Maaf, kami tidak dapat mengesan cara untuk mengesahkan anda pada masa ini.",
      "continue_with_email_button": "Teruskan",
      "auth_block_separator": "Atau",
      "continue_with_social_provider_button": "Teruskan dengan ${social_provider_name}",
      "continue_with_enterprise_provider_button": "Teruskan dengan ${enterprise_provider_name}",
      "no_account_description": "Tiada akaun?",
      "no_account_link": "Buat akaun"
    },
    "sign_up_page": {
      "page_title": "Daftar | ${business_name}",
      "heading": "Buat akaun",
      "description": "Bagus rasanya anda di sini",
      "invitation_description": "Anda telah dijemput untuk menyertai ${business_name}. Sila daftar masuk atau mendaftar untuk menerima jemputan.",
      "first_name_input_label": "Nama pertama",
      "first_name_input_error_required": "Sila masukkan nama pertama anda",
      "last_name_input_label": "Nama keluarga",
      "last_name_input_error_required": "Sila masukkan nama keluarga anda",
      "email_input_label": "E-mel",
      "email_input_error_required": "E-mel diperlukan",
      "email_input_error_invalid": "Masukkan e-mel yg sah",
      "email_input_error_invitation_mismatch": "E-mel mesti sepadan dengan e-mel yang dihantar jemputan kepada anda",
      "continue_with_email_button": "Daftar akaun",
      "auth_block_separator": "Atau",
      "continue_with_social_provider_button": "Teruskan dengan ${social_provider_name}",
      "continue_with_enterprise_provider_button": "Teruskan dengan ${enterprise_provider_name}",
      "already_have_an_account_description": "Telah memiliki akaun?",
      "already_have_an_account_link": "Daftar masuk",
      "disclaimer": "Dengan meneruskan, anda bersetuju dengan dasar kami",
      "disclaimer_privacy_link": "Dasar Privasi",
      "disclaimer_terms_of_use_link": "Terma Penggunaan",
      "disclaimer_clickwrap_input_label": "Terima dasar",
      "disclaimer_clickwrap_error_required": "Anda mestilah membaca dan menerima dasar untuk meneruskan",
      "disclaimer_dialog_heading": "Terima untuk meneruskan",
      "disclaimer_dialog_description": "Untuk meneruskan pendaftaran, kami memerlukan anda untuk membaca dan menerima dasar-dasar kami",
      "auth_form_error_terms_not_accepted": "Anda perlu membaca dan menerima dasar-dasar ini untuk meneruskan",
      "auth_form_error_no_auth_methods_enabled": "Maaf, kami tidak dapat mengesan cara untuk mengesahkan anda pada masa ini.",
      "auth_form_error_org_not_accepting_registrations": "Organisasi ini tidak menerima pendaftaran baru"
    },
    "choose_mfa_method_page": {
      "page_title": "Pilih pilihan MFA | ${business_name}",
      "heading": "Sahkan identiti anda",
      "description": "Pilih kaedah pengesahan",
      "authenticator_app_button": "Aplikasi pengesahan",
      "sms_button": "SMS",
      "email_button": "E-mel",
      "do_not_use_mfa_link": "Jangan gunakan pengesahan berbilang faktor"
    },
    "account_locked_page": {
      "page_title": "Akaun dikunci | ${business_name}",
      "heading": "Akaun dikunci",
      "description": "Anda telah memasukkan kod yg salah berulang kali dan akaun anda telah dikunci selama ${lockout_duration_minutes} minit",
      "go_back_button": "Kembali"
    },
    "password_setup_page": {
      "page_title": "Tetapkan kata laluan | ${business_name}",
      "heading": "Penetapan kata laluan",
      "description": "Sila masukkan kata laluan anda.",
      "password_input_label": "Kata laluan",
      "password_input_error_too_common": "Kata laluan ini terlalu biasa. Jadikannya lebih sukar untuk diteka.",
      "password_input_error_too_short": "Kata laluan perlu mengandungi sekurang-kurangnya 8 aksara",
      "password_input_error_extra_space": "Kata laluan tidak boleh bermula atau berakhir dengan jarak",
      "confirm_password_input_label": "Sahkan kata laluan",
      "confirm_password_input_error_mismatch": "Pastikan kata laluan adalaha sama",
      "continue_button": "Teruskan",
      "password_input_error_unknown_error": "Ralat dengan pengesahan"
    },
    "recovery_codes_page": {
      "page_title": "Kod pemulihan | ${business_name}",
      "heading": "Hampir disana",
      "description": "Salin kod pemulihan ini dan simpan di tempat yang selamat. Anda memerlukannya jika anda perlu mendaftar masuk tanpa peranti anda.",
      "copy_button": "Salin semua",
      "print_button": "Cetak",
      "continue_button": "Teruskan",
      "download_button": "Muat turun .txt",
      "recovery_codes_page_error_no_codes": "Tiada kod untuk ditunjukkan",
      "recovery_codes_page_error_already_viewed": "Nampaknya anda telah melihat kod pemulihan sekali, jadi kami tidak dapat menunjukkannya lagi. Jika anda memerlukan bantuan untuk log masuk, hubungi pentadbir akaun anda.",
      "back_home_button": "Kembali"
    },
    "subscribe_form_widget": {
      "page_title": "Langgan",
      "heading": "Kekal dengan maklumat terkini",
      "description": "Dengar daripada kami tentang kemas kini produk, berita dan acara",
      "name_input_label": "Nama pertama",
      "name_input_error_required": "Sila masukkan nama",
      "name_input_error_exceeds_max_length": "Nama terlalu panjang",
      "email_input_label": "E-mel",
      "email_input_error_invalid": "Masukkan e-mel yg sah",
      "email_input_error_required": "E-mel diperlukan",
      "email_input_error_duplicate_email_found": "E-mel ini telah melanggan",
      "continue_button": "Daftar",
      "success_heading": "Berjaya! Selamat datang.",
      "credit_powered_by": "Dikuasakan oleh"
    },
    "password_verify_page": {
      "page_title": "Sahkan kata laluan | ${business_name}",
      "heading": "Masukkan kata laluan anda",
      "description": "Masukkan kata laluan anda untuk ${email_address}",
      "password_input_label": "Kata laluan",
      "password_input_error_required": "Masukkan kata laluan anda",
      "password_input_error_incorrect": "Masukkan kata laluan yang sah",
      "password_input_error_too_short": "Kata laluan perlu mengandungi sekurang-kurangnya 8 aksara",
      "continue_button": "Teruskan",
      "cant_sign_in_description": "Can't sign in?",
      "cant_sign_in_link": "Reset password",
      "password_input_error_unknown_error": "Ralat dengan pengesahan"
    },
    "sms_verify_code_page": {
      "page_title": "Pengesahan berbilang faktor | ${business_name}",
      "heading": "Sahkan nombor telefon",
      "description": "Masukkan kod yang baru sahaja kami hantar ke ${phone_number}",
      "code_input_label": "Kod",
      "code_input_error_expired_code": "Kod pengesahan anda telah tamat tempoh, sila minta yg baru",
      "code_input_error_incorrect_code": "Sila masukkan kod pengesahan yang sah",
      "code_input_error_incorrect_code_length": "Kod pengesahan mestilah mengandungi 6 digit",
      "code_input_error_resend_requested_too_soon": "Tidak dapat menghantar kod yg lain buat masa sekarang. Sila cuba sebentar lagi.",
      "confirmation_code_input_error_unknown_error": "Ralat dalam proses pengesahan",
      "continue_button": "Sahkan",
      "didnt_receive_a_code_description": "Tidak menerima sebarang kod?",
      "didnt_receive_a_code_link": "Hantar kod semula",
      "choose_another_method_link": "Sila pilih kaedah yang lain"
    },
    "recovery_code_verify_page": {
      "page_title": "Gunakan kod pemulihan | ${business_name}",
      "heading": "Kod pemulihan",
      "description": "Masukkan salah satu dari kod pemulihan yang telah diberikan semasa proses pendaftaran awal.",
      "recovery_code_input_label": "Kod pemulihan",
      "continue_button": "Teruskan",
      "choose_another_method_link": "Sila pilih kaedah yang lain",
      "recovery_code_input_error_unknown_error": "Terdapat masalah membuat pengesahan dengan kod pemulihan ini",
      "recovery_code_input_error_required": "Masukkan kod pemulihan anda",
      "recovery_code_input_error_too_short": "Kod pemulihan perlu mengandungi sekurang-kurangnya 9 aksara",
      "recovery_code_input_error_invalid": "Masukkan kod pemulihan yang sah"
    },
    "verification_code_sms": {
      "description": "${generated_code} adalah kod sekali guna anda untuk mendaftar masuk ke ${business_name} @${receiver_domain} #${generated_code}"
    },
    "choose_organization_page": {
      "page_title": "Pilih organisasi | ${business_name}",
      "heading": "Dimanakah anda mahu mendaftar masuk?",
      "choose_org_select_label": "Daftarkan saya masuk ke",
      "choose_org_select_error_invalid": "Organisasi tidak sah",
      "continue_button": "Teruskan"
    },
    "request_access_page": {
      "page_title": "Dapatkan notifkasi awal",
      "heading": "Kami akan terus mengemaskini anda dan menghantar jemputan apabila akses telah tersedia",
      "description": "Kami akan terus mengemaskini dan memberitahu anda apabila jemputan anda sudah sedia.",
      "continue_button": "Mohon akses",
      "success_heading": "Terima kasih atas permohonan akses. Kami telah menambah anda dalam senarai dan akan memaklumkan kemaskini dalam masa terdekat.",
      "first_name_input_label": "Nama pertama",
      "first_name_input_error_required": "Sila masukkan nama pertama anda",
      "last_name_input_label": "Nama keluarga",
      "email_input_label": "E-mel",
      "email_input_error_invalid": "Masukkan e-mel yg sah",
      "email_input_error_required": "E-mel diperlukan",
      "email_input_error_duplicate_email_found": "Alamat e-mel ini telah didaftarkan",
      "success_description": "Terima kasih atas permohonan akses ke ${business_name}. Kami telah menambah anda dalam senarai pelanggan dan kami akan memaklumkan sekiranya jemputan telah tersedia.",
      "success_link_url": "Kembali ke laman ${business_name}"
    },
    "sign_in_confirm_code_page": {
      "page_title": "Sahkan kod | ${business_name}",
      "heading": "Semak e-mel anda",
      "description": "Masukkan kod yang baru sahaja kami hantar ke ${email_address}",
      "resent_code": "Kami baru sahaja menghantar kod yang baru ke ${email_address}",
      "code_input_label": "Kod",
      "code_input_error_expired_code": "Kod pengesahan anda telah tamat tempoh, sila minta yg baru",
      "code_input_error_incorrect_code": "Sila masukkan kod pengesahan yang sah",
      "code_input_error_incorrect_code_length": "Kod pengesahan mestilah mengandungi 6 digit",
      "code_input_error_resend_requested_too_soon": "Tidak dapat menghantar kod yg lain buat masa sekarang. Sila cuba sebentar lagi.",
      "continue_button": "Teruskan",
      "didnt_receive_a_code_link": "Hantar kod semula",
      "didnt_receive_a_code_description": "Tidak menerima sebarang kod?",
      "warning_too_many_incorrect_attempts": "Terlalu banyak kod yang salah dimasukkan, jadi kami baru sahaja menghantar satu kod yang baru kepada ${email_address}",
      "choose_another_method_link": "Sila pilih kaedah yang lain"
    },
    "sign_up_confirm_code_page": {
      "page_title": "Sahkan kod | ${business_name}",
      "heading": "Semak e-mel anda",
      "description": "Masukkan kod yang baru sahaja kami hantar ke ${email_address}",
      "finish_sign_up_code_description": "To continue, enter the code we just sent to ${email_address}",
      "continue_sign_up_code_description": "To continue, enter the code we just sent to ${email_address}",
      "resent_code": "Kami baru sahaja menghantar kod yang baru ke ${email_address}",
      "code_input_label": "Kod",
      "code_input_error_expired_code": "Kod pengesahan anda telah tamat tempoh, sila minta yg baru",
      "code_input_error_incorrect_code": "Sila masukkan kod pengesahan yang sah",
      "code_input_error_incorrect_code_length": "Kod pengesahan mestilah mengandungi 6 digit",
      "code_input_error_resend_requested_too_soon": "Tidak dapat menghantar kod yg lain buat masa sekarang. Sila cuba sebentar lagi.",
      "didnt_receive_a_code_description": "Tidak menerima sebarang kod?",
      "didnt_receive_a_code_link": "Hantar kod semula",
      "continue_button": "Teruskan",
      "warning_too_many_incorrect_attempts": "Terlalu banyak kod yang salah dimasukkan, jadi kami baru sahaja menghantar satu kod yang baru kepada ${email_address}",
      "choose_another_method_link": "Sila pilih kaedah yang lain"
    },
    "authenticator_app_manual_page": {
      "page_title": "Aplikasi pengesahan | ${business_name}",
      "heading": "Aplikasi pengesahan",
      "description": "Masukkan kod berikut dalam aplikasi pengesahan pilihan anda. Kemudian masukkan kod sekali guna yang anda terima di bawah.",
      "code_input_label": "Kod sekali guna",
      "code_input_error_required": "Sila masukkan kod pengesahan yang sah",
      "code_input_error_expired_code": "Kod pengesahan anda telah tamat tempoh, sila minta yg baru",
      "code_input_error_incorrect_code_length": "Kod pengesahan mestilah mengandungi 6 digit",
      "code_input_error_incorrect_code": "Sila masukkan kod pengesahan yang sah",
      "continue_button": "Teruskan",
      "choose_another_method_link": "Sila pilih kaedah yang lain"
    },
    "authenticator_app_qr_code_page": {
      "page_title": "Pengesahan berbilang faktor | ${business_name}",
      "heading": "Aplikasi pengesahan",
      "description": "Imbas kod QR di bawah menggunakan aplikasi pengesahan pilihan anda. Masukkan kod sekali guna yang anda terima di bawah.",
      "code_input_label": "Kod sekali guna",
      "code_input_error_required": "Sila masukkan kod pengesahan yang sah",
      "code_input_error_expired_code": "Kod pengesahan anda telah tamat tempoh, sila minta yg baru",
      "code_input_error_incorrect_code": "Sila masukkan kod pengesahan yang sah",
      "code_input_error_incorrect_code_length": "Kod pengesahan mestilah mengandungi 6 digit",
      "continue_button": "Teruskan",
      "trouble_scanning_link": "Masalah dengan pengimbasan?",
      "choose_another_method_link": "Sila pilih kaedah yang lain"
    },
    "email_address_verification_email": {
      "email_body": "Kod ini akan tamat dalam masa 2 jam. Jika anda rasa anda tidak sepatutnya menerima e-mel ini, anda boleh mengabaikannya dengan selamat",
      "email_preview": "Sila gunakan kod dibawah ini untuk mengesahkan alamat e-mel anda dan meneruskan ke ${business_name}",
      "email_subject": "Kod pengesahan e-mel",
      "email_greeting": "Hai disana,",
      "email_disclaimer": "Anda menerima e-mel ini kerana anda telah memohon kod pengesahan dari ${business_name}"
    }
  }
}